MANIFEST.in
README
requirements.txt
setup.py
ajenti.plugin.datetime.egg-info/PKG-INFO
ajenti.plugin.datetime.egg-info/SOURCES.txt
ajenti.plugin.datetime.egg-info/dependency_links.txt
ajenti.plugin.datetime.egg-info/requires.txt
ajenti.plugin.datetime.egg-info/top_level.txt
ajenti_plugin_datetime/README.md
ajenti_plugin_datetime/__init__.py
ajenti_plugin_datetime/api.py
ajenti_plugin_datetime/main.py
ajenti_plugin_datetime/plugin.yml
ajenti_plugin_datetime/requirements.txt
ajenti_plugin_datetime/views.py
ajenti_plugin_datetime/locale/app.pot
ajenti_plugin_datetime/locale/af/LC_MESSAGES/app.js
ajenti_plugin_datetime/locale/af/LC_MESSAGES/app.po
ajenti_plugin_datetime/locale/ar/LC_MESSAGES/app.js
ajenti_plugin_datetime/locale/ar/LC_MESSAGES/app.po
ajenti_plugin_datetime/locale/be/LC_MESSAGES/app.js
ajenti_plugin_datetime/locale/be/LC_MESSAGES/app.po
ajenti_plugin_datetime/locale/bg/LC_MESSAGES/app.js
ajenti_plugin_datetime/locale/bg/LC_MESSAGES/app.po
ajenti_plugin_datetime/locale/bn/LC_MESSAGES/app.js
ajenti_plugin_datetime/locale/bn/LC_MESSAGES/app.po
ajenti_plugin_datetime/locale/bs/LC_MESSAGES/app.js
ajenti_plugin_datetime/locale/bs/LC_MESSAGES/app.po
ajenti_plugin_datetime/locale/ca/LC_MESSAGES/app.js
ajenti_plugin_datetime/locale/ca/LC_MESSAGES/app.po
ajenti_plugin_datetime/locale/cs/LC_MESSAGES/app.js
ajenti_plugin_datetime/locale/cs/LC_MESSAGES/app.po
ajenti_plugin_datetime/locale/da/LC_MESSAGES/app.js
ajenti_plugin_datetime/locale/da/LC_MESSAGES/app.po
ajenti_plugin_datetime/locale/de/LC_MESSAGES/app.js
ajenti_plugin_datetime/locale/de/LC_MESSAGES/app.po
ajenti_plugin_datetime/locale/el/LC_MESSAGES/app.js
ajenti_plugin_datetime/locale/el/LC_MESSAGES/app.po
ajenti_plugin_datetime/locale/en/LC_MESSAGES/app.po
ajenti_plugin_datetime/locale/eo/LC_MESSAGES/app.js
ajenti_plugin_datetime/locale/eo/LC_MESSAGES/app.po
ajenti_plugin_datetime/locale/es-ES/LC_MESSAGES/app.js
ajenti_plugin_datetime/locale/es-ES/LC_MESSAGES/app.po
ajenti_plugin_datetime/locale/et/LC_MESSAGES/app.js
ajenti_plugin_datetime/locale/et/LC_MESSAGES/app.po
ajenti_plugin_datetime/locale/fa/LC_MESSAGES/app.js
ajenti_plugin_datetime/locale/fa/LC_MESSAGES/app.po
ajenti_plugin_datetime/locale/fi/LC_MESSAGES/app.js
