Metadata-Version: 1.2
Name: ajenti.plugin.datetime
Version: 0.41
Summary: Date & time
Home-page: https://ajenti.org
Author: Ajenti project
Author-email: e@ajenti.org
License: UNKNOWN
Platform: UNKNOWN
Requires-Python: >=3
